<step title="BackgroundTrace" date="2025-07-14T09:56:24.543" instance="2b261b" url="/api/zipdeploy" method="POST" >
  <step title="Creating temporary deployment - FetchDeploymentManager" date="2025-07-14T09:56:24.659" /><!-- duration: 3ms -->
  <step title="Creating temporary deployment" date="2025-07-14T09:56:24.669" /><!-- duration: 53ms -->
  <step title="Performing fetch based deployment" date="2025-07-14T09:56:24.765" >
    <step title="Cleaning up temp folders from previous zip deployments and extracting pushed zip file /tmp/zipdeploy/7278bf66-1bda-4927-91bb-d33621265e4d.zip (0.02 MB) to /tmp/zipdeploy/extracted" date="2025-07-14T09:56:25.888" >
      <step title="ChmodRecursive Process exited with total time taken in ms: 90" date="2025-07-14T09:56:26.068" /><!-- duration: 20ms -->
    </step><!-- duration: 212ms -->
    <step title="Deployment timer started" date="2025-07-14T09:56:28.136" >
      <step title="DeploymentManager.Deploy(id:1cc10bcb-2b0a-4106-9d43-1097b8b7d507)" date="2025-07-14T09:56:28.148" >
        <step title="Collecting changeset information" date="2025-07-14T09:56:28.196" /><!-- duration: 129ms -->
        <step title="Updating submodules" date="2025-07-14T09:56:28.341" /><!-- duration: 1118ms -->
        <step title="Determining deployment builder" date="2025-07-14T09:56:29.730" >
          <step title="Builder is OryxBuilder" date="2025-07-14T09:56:29.757" /><!-- duration: 22ms -->
        </step><!-- duration: 54ms -->
        <step title="PreDeployment: context.CleanOutputPath False" date="2025-07-14T09:56:29.879" >
          <step title="PreDeployment: context.OutputPath /home/site/wwwroot" date="2025-07-14T09:56:30.057" >
            <step title="Building" date="2025-07-14T09:56:30.236" >
              <step title="Executing external process" date="2025-07-14T09:56:31.094" type="process" path="bash" arguments="-c &quot;oryx build /tmp/zipdeploy/extracted -o /home/site/wwwroot --platform python --platform-version 3.11 -p virtualenv_name=antenv --log-file /tmp/build-debug.log  -i /tmp/8ddc2bcb4b80302 --compress-destination-dir | tee /tmp/oryx-build.log ; exit $PIPESTATUS &quot;" /><!-- duration: 108870ms -->
              <step title="Using PythonDeploymentLogParser" date="2025-07-14T09:58:20.308" /><!-- duration: 5ms -->
              <step title="Triggering recycle (preview mode disabled)." date="2025-07-14T09:58:21.341" /><!-- duration: 15ms -->
              <step title="Modified file to trigger a restart of the app container." date="2025-07-14T09:58:21.396" /><!-- duration: 3ms -->
              <step title="Skip function trigger and logicapp sync because function is not enabled." date="2025-07-14T09:58:21.404" /><!-- duration: 3ms -->
              <step title="Purge deployment items" date="2025-07-14T09:58:22.346" >
                <step title="Remove 2b712a2f-, Success, received at 05/21/2025 21:25:16" date="2025-07-14T09:58:22.415" /><!-- duration: 6ms -->
              </step><!-- duration: 78ms -->
            </step><!-- duration: 112249ms -->
          </step><!-- duration: 112432ms -->
          <step title="Cleaning up temp files" date="2025-07-14T09:58:22.491" /><!-- duration: 361ms -->
          <step title="Cleaning up temp files" date="2025-07-14T09:58:22.854" /><!-- duration: 507ms -->
          <step title="Reloading status file with latest updates" date="2025-07-14T09:58:23.385" >
            <step title="WebHooksManager.PublishEventAsync: PostDeployment" date="2025-07-14T09:58:23.388" /><!-- duration: 51ms -->
          </step><!-- duration: 57ms -->
          <step title="Cleaning up temporary deployment - fetch deployment was successful" date="2025-07-14T09:58:23.449" /><!-- duration: 3ms -->
        </step><!-- duration: 113670ms -->
      </step><!-- duration: 115413ms -->
